ragwrangler/__init__.py
ragwrangler/db.py
ragwrangler/example_usage.py
ragwrangler/prompts.py
ragwrangler/rag.py
ragwrangler/utils.py
ragwrangler-0.1.4.dist-info/METADATA
ragwrangler-0.1.4.dist-info/WHEEL
ragwrangler-0.1.4.dist-info/top_level.txt
ragwrangler-0.1.4.dist-info/RECORD
