Metadata-Version: 2.1
Name: ragwrangler
Version: 0.1.4
Summary: A simple RAG (Retrieval-Augumented Generation) Task Manager
Author-email: JP Hwang <me@jphwang.com>
Keywords: rag,generation,retrieval,weaviate,openai
Requires-Python: >=3.8
Requires-Dist: openai
Requires-Dist: weaviate-client
